MANIFEST.in
README.txt
setup.cfg
setup.py
collective/__init__.py
collective.cdn.alternatehostname.egg-info/PKG-INFO
collective.cdn.alternatehostname.egg-info/SOURCES.txt
collective.cdn.alternatehostname.egg-info/dependency_links.txt
collective.cdn.alternatehostname.egg-info/entry_points.txt
collective.cdn.alternatehostname.egg-info/namespace_packages.txt
collective.cdn.alternatehostname.egg-info/not-zip-safe
collective.cdn.alternatehostname.egg-info/requires.txt
collective.cdn.alternatehostname.egg-info/top_level.txt
collective/cdn/__init__.py
collective/cdn/alternatehostname/README.txt
collective/cdn/alternatehostname/__init__.py
collective/cdn/alternatehostname/config.py
collective/cdn/alternatehostname/configure.zcml
collective/cdn/alternatehostname/provider.py
collective/cdn/alternatehostname/tests.py
collective/cdn/alternatehostname/version.txt
collective/cdn/alternatehostname/docs/__init__.py
collective/cdn/alternatehostname/docs/browser.txt
docs/HISTORY.txt
docs/INSTALL.txt
docs/LICENSE.GPL
docs/LICENSE.txt