Metadata-Version: 1.0
Name: collective.cdn.alternatehostname
Version: 0.5
Summary: Alternate hostname CDN support for Plone
Home-page: http://www.simplesconsultoria.com.br/
Author: Simples Consultoria
Author-email: products@simplesconsultoria.com.br
License: GPL
Keywords: plone plone4 cdn content simplesconsultoria
Platform: UNKNOWN
Classifier: Framework :: Plone
Classifier: Framework :: Zope2
Classifier: Framework :: Zope3
Classifier: Programming Language :: Python
Classifier: Topic :: Software Development :: Libraries :: Python Modules
